django_jellyglass-0.3.0.dist-info/RECORD
django_jellyglass-0.3.0.dist-info/DESCRIPTION.rst
django_jellyglass-0.3.0.dist-info/top_level.txt
django_jellyglass-0.3.0.dist-info/WHEEL
django_jellyglass-0.3.0.dist-info/metadata.json
django_jellyglass-0.3.0.dist-info/METADATA
jellyglass/__init__.py
jellyglass/views.py
jellyglass/admin.py
jellyglass/models.py
jellyglass/urls.py
jellyglass/utils.py
jellyglass/apps.py
jellyglass/migrations/__init__.py
jellyglass/migrations/0001_initial.py
jellyglass/static/css/wordpress/login.min.css
jellyglass/static/css/wordpress/dashicons.min.css
jellyglass/static/css/wordpress/buttons.min.css
jellyglass/static/img/wordpress/wordpress-logo.svg
jellyglass/templates/jellyglass/django.html
jellyglass/templates/jellyglass/wordpress.html
